[
    {
        "trip_id":2153,
        "arrival_time":"07:52:00"
    },
    {
        "trip_id":2154,
        "arrival_time":"09:04:00"
    },
    {
        "trip_id":2155,
        "arrival_time":"10:16:00"
    },
    {
        "trip_id":2156,
        "arrival_time":"10:52:00"
    },
    {
        "trip_id":2157,
        "arrival_time":"11:28:00"
    },
    {
        "trip_id":2158,
        "arrival_time":"12:04:00"
    },
    {
        "trip_id":2159,
        "arrival_time":"12:40:00"
    },
    {
        "trip_id":2160,
        "arrival_time":"13:16:00"
    },
    {
        "trip_id":2161,
        "arrival_time":"13:52:00"
    },
    {
        "trip_id":2162,
        "arrival_time":"14:28:00"
    },
    {
        "trip_id":2163,
        "arrival_time":"15:04:00"
    },
    {
        "trip_id":2164,
        "arrival_time":"15:40:00"
    },
    {
        "trip_id":2165,
        "arrival_time":"16:16:00"
    },
    {
        "trip_id":2166,
        "arrival_time":"16:52:00"
    },
    {
        "trip_id":2167,
        "arrival_time":"17:28:00"
    },
    {
        "trip_id":2168,
        "arrival_time":"18:04:00"
    },
    {
        "trip_id":2169,
        "arrival_time":"18:40:00"
    },
    {
        "trip_id":2170,
        "arrival_time":"19:16:00"
    },
    {
        "trip_id":2171,
        "arrival_time":"19:52:00"
    },
    {
        "trip_id":2172,
        "arrival_time":"20:28:00"
    },
    {
        "trip_id":2173,
        "arrival_time":"21:04:00"
    }
]