[
    {
        "trip_id":792,
        "arrival_time":"06:32:00"
    },
    {
        "trip_id":793,
        "arrival_time":"07:22:00"
    },
    {
        "trip_id":794,
        "arrival_time":"08:20:00"
    },
    {
        "trip_id":795,
        "arrival_time":"09:10:00"
    },
    {
        "trip_id":796,
        "arrival_time":"10:00:00"
    },
    {
        "trip_id":239,
        "arrival_time":"11:14:00"
    },
    {
        "trip_id":240,
        "arrival_time":"12:03:00"
    },
    {
        "trip_id":241,
        "arrival_time":"13:28:00"
    },
    {
        "trip_id":242,
        "arrival_time":"14:34:00"
    },
    {
        "trip_id":243,
        "arrival_time":"15:14:00"
    },
    {
        "trip_id":244,
        "arrival_time":"16:02:00"
    },
    {
        "trip_id":245,
        "arrival_time":"16:53:00"
    },
    {
        "trip_id":247,
        "arrival_time":"17:50:00"
    },
    {
        "trip_id":249,
        "arrival_time":"18:16:00"
    },
    {
        "trip_id":251,
        "arrival_time":"19:13:00"
    },
    {
        "trip_id":253,
        "arrival_time":"20:23:00"
    }
]