[
    {
        "trip_id":4857,
        "arrival_time":"07:14:00"
    },
    {
        "trip_id":4859,
        "arrival_time":"08:12:00"
    },
    {
        "trip_id":4861,
        "arrival_time":"09:02:00"
    },
    {
        "trip_id":4863,
        "arrival_time":"09:52:00"
    },
    {
        "trip_id":4865,
        "arrival_time":"11:08:00"
    },
    {
        "trip_id":4866,
        "arrival_time":"12:15:00"
    },
    {
        "trip_id":4867,
        "arrival_time":"13:22:00"
    },
    {
        "trip_id":4868,
        "arrival_time":"14:29:00"
    },
    {
        "trip_id":4869,
        "arrival_time":"15:14:00"
    },
    {
        "trip_id":4870,
        "arrival_time":"15:54:00"
    },
    {
        "trip_id":4871,
        "arrival_time":"16:48:00"
    },
    {
        "trip_id":4872,
        "arrival_time":"17:04:00"
    },
    {
        "trip_id":4873,
        "arrival_time":"17:47:00"
    }
]