[
    {
        "trip_id":2299,
        "arrival_time":"07:50:00"
    },
    {
        "trip_id":2300,
        "arrival_time":"09:02:00"
    },
    {
        "trip_id":2301,
        "arrival_time":"10:14:00"
    },
    {
        "trip_id":2302,
        "arrival_time":"10:50:00"
    },
    {
        "trip_id":2303,
        "arrival_time":"11:26:00"
    },
    {
        "trip_id":2304,
        "arrival_time":"12:02:00"
    },
    {
        "trip_id":2305,
        "arrival_time":"12:38:00"
    },
    {
        "trip_id":2306,
        "arrival_time":"13:14:00"
    },
    {
        "trip_id":2307,
        "arrival_time":"13:50:00"
    },
    {
        "trip_id":2308,
        "arrival_time":"14:26:00"
    },
    {
        "trip_id":2309,
        "arrival_time":"15:02:00"
    },
    {
        "trip_id":2310,
        "arrival_time":"15:38:00"
    },
    {
        "trip_id":2311,
        "arrival_time":"16:14:00"
    },
    {
        "trip_id":2312,
        "arrival_time":"16:50:00"
    },
    {
        "trip_id":2313,
        "arrival_time":"17:26:00"
    },
    {
        "trip_id":2314,
        "arrival_time":"18:02:00"
    },
    {
        "trip_id":2315,
        "arrival_time":"18:38:00"
    },
    {
        "trip_id":2316,
        "arrival_time":"19:14:00"
    },
    {
        "trip_id":2317,
        "arrival_time":"19:50:00"
    },
    {
        "trip_id":2318,
        "arrival_time":"20:26:00"
    },
    {
        "trip_id":2319,
        "arrival_time":"21:02:00"
    }
]