[
    {
        "trip_id":3114,
        "arrival_time":"05:22:00"
    },
    {
        "trip_id":3115,
        "arrival_time":"06:22:00"
    },
    {
        "trip_id":3116,
        "arrival_time":"07:24:00"
    },
    {
        "trip_id":3117,
        "arrival_time":"08:24:00"
    },
    {
        "trip_id":3118,
        "arrival_time":"09:26:00"
    },
    {
        "trip_id":3119,
        "arrival_time":"10:28:00"
    },
    {
        "trip_id":3120,
        "arrival_time":"11:34:00"
    },
    {
        "trip_id":3121,
        "arrival_time":"12:39:00"
    },
    {
        "trip_id":3122,
        "arrival_time":"14:02:00"
    },
    {
        "trip_id":3123,
        "arrival_time":"15:07:00"
    },
    {
        "trip_id":3124,
        "arrival_time":"16:12:00"
    },
    {
        "trip_id":3125,
        "arrival_time":"17:44:00"
    },
    {
        "trip_id":3126,
        "arrival_time":"19:14:00"
    },
    {
        "trip_id":3127,
        "arrival_time":"21:03:00"
    }
]