[
    {
        "trip_id":2920,
        "arrival_time":"06:16:00"
    },
    {
        "trip_id":2921,
        "arrival_time":"07:16:00"
    },
    {
        "trip_id":2922,
        "arrival_time":"08:18:00"
    },
    {
        "trip_id":2923,
        "arrival_time":"09:20:00"
    },
    {
        "trip_id":2924,
        "arrival_time":"10:22:00"
    },
    {
        "trip_id":2925,
        "arrival_time":"11:27:00"
    },
    {
        "trip_id":2926,
        "arrival_time":"12:50:00"
    },
    {
        "trip_id":2927,
        "arrival_time":"13:55:00"
    },
    {
        "trip_id":2928,
        "arrival_time":"15:00:00"
    },
    {
        "trip_id":2929,
        "arrival_time":"15:45:00"
    },
    {
        "trip_id":2930,
        "arrival_time":"16:30:00"
    },
    {
        "trip_id":2931,
        "arrival_time":"17:15:00"
    },
    {
        "trip_id":2932,
        "arrival_time":"18:00:00"
    },
    {
        "trip_id":2933,
        "arrival_time":"18:45:00"
    },
    {
        "trip_id":2934,
        "arrival_time":"19:51:00"
    }
]