[
    {
        "trip_id":426,
        "arrival_time":"08:56:00"
    },
    {
        "trip_id":427,
        "arrival_time":"10:02:00"
    },
    {
        "trip_id":428,
        "arrival_time":"11:06:00"
    },
    {
        "trip_id":429,
        "arrival_time":"12:10:00"
    },
    {
        "trip_id":430,
        "arrival_time":"13:14:00"
    },
    {
        "trip_id":431,
        "arrival_time":"14:18:00"
    },
    {
        "trip_id":432,
        "arrival_time":"15:22:00"
    },
    {
        "trip_id":433,
        "arrival_time":"16:26:00"
    },
    {
        "trip_id":434,
        "arrival_time":"17:30:00"
    },
    {
        "trip_id":435,
        "arrival_time":"18:34:00"
    },
    {
        "trip_id":436,
        "arrival_time":"19:38:00"
    },
    {
        "trip_id":437,
        "arrival_time":"20:42:00"
    }
]