[
    {
        "trip_id":2657,
        "arrival_time":"06:13:00"
    },
    {
        "trip_id":2658,
        "arrival_time":"06:55:00"
    },
    {
        "trip_id":2659,
        "arrival_time":"07:37:00"
    },
    {
        "trip_id":2660,
        "arrival_time":"08:19:00"
    },
    {
        "trip_id":2661,
        "arrival_time":"09:01:00"
    },
    {
        "trip_id":2662,
        "arrival_time":"09:43:00"
    },
    {
        "trip_id":2663,
        "arrival_time":"10:48:00"
    },
    {
        "trip_id":2664,
        "arrival_time":"11:51:00"
    },
    {
        "trip_id":2665,
        "arrival_time":"12:54:00"
    },
    {
        "trip_id":2666,
        "arrival_time":"13:57:00"
    },
    {
        "trip_id":2667,
        "arrival_time":"15:00:00"
    },
    {
        "trip_id":2668,
        "arrival_time":"16:03:00"
    },
    {
        "trip_id":2669,
        "arrival_time":"16:51:00"
    },
    {
        "trip_id":2670,
        "arrival_time":"17:36:00"
    },
    {
        "trip_id":2671,
        "arrival_time":"18:21:00"
    },
    {
        "trip_id":2672,
        "arrival_time":"19:06:00"
    },
    {
        "trip_id":2673,
        "arrival_time":"20:06:00"
    },
    {
        "trip_id":2674,
        "arrival_time":"21:18:00"
    }
]